roiti/gie/VERSION
roiti/gie/__init__.py
roiti/gie/exceptions.py
roiti/gie/gie_pandas_client.py
roiti/gie/gie_raw_client.py
roiti/gie/lookup_functions.py
roiti/gie/mappings/__init__.py
roiti/gie/mappings/agsi_company.py
roiti/gie/mappings/agsi_country.py
roiti/gie/mappings/agsi_facility.py
roiti/gie/mappings/alsi_company.py
roiti/gie/mappings/alsi_country.py
roiti/gie/mappings/alsi_facility.py
roiti/gie/mappings/api_mappings.py
roiti_gie-1.0.1.dist-info/LICENSE
roiti_gie-1.0.1.dist-info/METADATA
roiti_gie-1.0.1.dist-info/WHEEL
roiti_gie-1.0.1.dist-info/top_level.txt
roiti_gie-1.0.1.dist-info/RECORD
