Metadata-Version: 2.1
Name: roiti-gie
Version: 1.0.1
Summary: A library to query GIE ALSI/AGSI data
Author: Roiti Ltd.
Author-email: opensource@roiti.com
Maintainer-email: opensource@roiti.com
License: MIT License
Classifier: Programming Language :: Python :: 3
Classifier: Operating System :: OS Independent
Requires-Python: >=3.7
License-File: LICENSE
Requires-Dist: aiohttp (<4.0.0,>=3.8.0)
Requires-Dist: pandas (>=1.0)
